<annotation>
	<folder>500</folder>
	<filename>1142.png</filename>
	<path>C:\Users\sdh17\Documents\NN\500\1142.png</path>
	<source>
		<database>Unknown</database>
	</source>
	<size>
		<width>960</width>
		<height>600</height>
		<depth>3</depth>
	</size>
	<segmented>0</segmented>
	<object>
		<name>aspa</name>
		<pose>Unspecified</pose>
		<truncated>1</truncated>
		<difficult>0</difficult>
		<bndbox>
			<xmin>141</xmin>
			<ymin>471</ymin>
			<xmax>213</xmax>
			<ymax>600</ymax>
		</bndbox>
	</object>
	<object>
		<name>aspa</name>
		<pose>Unspecified</pose>
		<truncated>0</truncated>
		<difficult>0</difficult>
		<bndbox>
			<xmin>566</xmin>
			<ymin>208</ymin>
			<xmax>597</xmax>
			<ymax>503</ymax>
		</bndbox>
	</object>
	<object>
		<name>aspa</name>
		<pose>Unspecified</pose>
		<truncated>1</truncated>
		<difficult>0</difficult>
		<bndbox>
			<xmin>468</xmin>
			<ymin>1</ymin>
			<xmax>504</xmax>
			<ymax>178</ymax>
		</bndbox>
	</object>
	<object>
		<name>aspa</name>
		<pose>Unspecified</pose>
		<truncated>1</truncated>
		<difficult>0</difficult>
		<bndbox>
			<xmin>435</xmin>
			<ymin>1</ymin>
			<xmax>452</xmax>
			<ymax>27</ymax>
		</bndbox>
	</object>
	<object>
		<name>aspa</name>
		<pose>Unspecified</pose>
		<truncated>1</truncated>
		<difficult>0</difficult>
		<bndbox>
			<xmin>600</xmin>
			<ymin>1</ymin>
			<xmax>633</xmax>
			<ymax>89</ymax>
		</bndbox>
	</object>
	<object>
		<name>aspa</name>
		<pose>Unspecified</pose>
		<truncated>1</truncated>
		<difficult>0</difficult>
		<bndbox>
			<xmin>617</xmin>
			<ymin>1</ymin>
			<xmax>637</xmax>
			<ymax>83</ymax>
		</bndbox>
	</object>
	<object>
		<name>aspa</name>
		<pose>Unspecified</pose>
		<truncated>0</truncated>
		<difficult>0</difficult>
		<bndbox>
			<xmin>494</xmin>
			<ymin>345</ymin>
			<xmax>528</xmax>
			<ymax>477</ymax>
		</bndbox>
	</object>
</annotation>
