<annotation>
	<folder>All</folder>
	<filename>b2_176.png</filename>
	<path>/media/aspa2/Data/training_images/All/b2_176.png</path>
	<source>
		<database>Unknown</database>
	</source>
	<size>
		<width>576</width>
		<height>360</height>
		<depth>3</depth>
	</size>
	<segmented>0</segmented>
	<object>
		<name>aspa</name>
		<pose>Unspecified</pose>
		<truncated>1</truncated>
		<difficult>0</difficult>
		<bndbox>
			<xmin>323</xmin>
			<ymin>302</ymin>
			<xmax>342</xmax>
			<ymax>360</ymax>
		</bndbox>
	</object>
	<object>
		<name>aspa</name>
		<pose>Unspecified</pose>
		<truncated>0</truncated>
		<difficult>0</difficult>
		<bndbox>
			<xmin>70</xmin>
			<ymin>292</ymin>
			<xmax>121</xmax>
			<ymax>312</ymax>
		</bndbox>
	</object>
	<object>
		<name>aspa</name>
		<pose>Unspecified</pose>
		<truncated>0</truncated>
		<difficult>0</difficult>
		<bndbox>
			<xmin>56</xmin>
			<ymin>273</ymin>
			<xmax>84</xmax>
			<ymax>299</ymax>
		</bndbox>
	</object>
	<object>
		<name>aspa</name>
		<pose>Unspecified</pose>
		<truncated>0</truncated>
		<difficult>0</difficult>
		<bndbox>
			<xmin>325</xmin>
			<ymin>69</ymin>
			<xmax>335</xmax>
			<ymax>94</ymax>
		</bndbox>
	</object>
	<object>
		<name>aspa</name>
		<pose>Unspecified</pose>
		<truncated>0</truncated>
		<difficult>0</difficult>
		<bndbox>
			<xmin>290</xmin>
			<ymin>59</ymin>
			<xmax>302</xmax>
			<ymax>83</ymax>
		</bndbox>
	</object>
	<object>
		<name>aspa</name>
		<pose>Unspecified</pose>
		<truncated>0</truncated>
		<difficult>0</difficult>
		<bndbox>
			<xmin>301</xmin>
			<ymin>79</ymin>
			<xmax>310</xmax>
			<ymax>100</ymax>
		</bndbox>
	</object>
</annotation>
