<annotation>
	<folder>All</folder>
	<filename>k3_59.png</filename>
	<path>/media/aspa2/Data/training_images/All/k3_59.png</path>
	<source>
		<database>Unknown</database>
	</source>
	<size>
		<width>576</width>
		<height>360</height>
		<depth>3</depth>
	</size>
	<segmented>0</segmented>
	<object>
		<name>aspa</name>
		<pose>Unspecified</pose>
		<truncated>0</truncated>
		<difficult>0</difficult>
		<bndbox>
			<xmin>258</xmin>
			<ymin>186</ymin>
			<xmax>315</xmax>
			<ymax>204</ymax>
		</bndbox>
	</object>
	<object>
		<name>aspa</name>
		<pose>Unspecified</pose>
		<truncated>1</truncated>
		<difficult>0</difficult>
		<bndbox>
			<xmin>1</xmin>
			<ymin>264</ymin>
			<xmax>35</xmax>
			<ymax>312</ymax>
		</bndbox>
	</object>
	<object>
		<name>aspa</name>
		<pose>Unspecified</pose>
		<truncated>0</truncated>
		<difficult>0</difficult>
		<bndbox>
			<xmin>383</xmin>
			<ymin>223</ymin>
			<xmax>394</xmax>
			<ymax>255</ymax>
		</bndbox>
	</object>
</annotation>
