<annotation>
	<folder>All</folder>
	<filename>k3_63.png</filename>
	<path>/media/aspa2/Data/training_images/All/k3_63.png</path>
	<source>
		<database>Unknown</database>
	</source>
	<size>
		<width>576</width>
		<height>360</height>
		<depth>3</depth>
	</size>
	<segmented>0</segmented>
	<object>
		<name>aspa</name>
		<pose>Unspecified</pose>
		<truncated>0</truncated>
		<difficult>0</difficult>
		<bndbox>
			<xmin>414</xmin>
			<ymin>240</ymin>
			<xmax>428</xmax>
			<ymax>294</ymax>
		</bndbox>
	</object>
	<object>
		<name>aspa</name>
		<pose>Unspecified</pose>
		<truncated>0</truncated>
		<difficult>0</difficult>
		<bndbox>
			<xmin>274</xmin>
			<ymin>72</ymin>
			<xmax>299</xmax>
			<ymax>133</ymax>
		</bndbox>
	</object>
	<object>
		<name>aspa</name>
		<pose>Unspecified</pose>
		<truncated>0</truncated>
		<difficult>0</difficult>
		<bndbox>
			<xmin>305</xmin>
			<ymin>74</ymin>
			<xmax>326</xmax>
			<ymax>110</ymax>
		</bndbox>
	</object>
</annotation>
