<annotation>
	<folder>train</folder>
	<filename>10153.png</filename>
	<path>/home/aspa2/Neural_Networks/kaimai_simplified/Images/train/10153.png</path>
	<source>
		<database>Unknown</database>
	</source>
	<size>
		<width>960</width>
		<height>600</height>
		<depth>3</depth>
	</size>
	<segmented>0</segmented>
	<object>
		<name>aspa</name>
		<pose>Unspecified</pose>
		<truncated>1</truncated>
		<difficult>0</difficult>
		<bndbox>
			<xmin>130</xmin>
			<ymin>476</ymin>
			<xmax>322</xmax>
			<ymax>600</ymax>
		</bndbox>
	</object>
	<object>
		<name>aspa</name>
		<pose>Unspecified</pose>
		<truncated>0</truncated>
		<difficult>0</difficult>
		<bndbox>
			<xmin>479</xmin>
			<ymin>394</ymin>
			<xmax>538</xmax>
			<ymax>552</ymax>
		</bndbox>
	</object>
	<object>
		<name>aspa</name>
		<pose>Unspecified</pose>
		<truncated>0</truncated>
		<difficult>0</difficult>
		<bndbox>
			<xmin>449</xmin>
			<ymin>390</ymin>
			<xmax>487</xmax>
			<ymax>434</ymax>
		</bndbox>
	</object>
	<object>
		<name>aspa</name>
		<pose>Unspecified</pose>
		<truncated>1</truncated>
		<difficult>0</difficult>
		<bndbox>
			<xmin>487</xmin>
			<ymin>1</ymin>
			<xmax>505</xmax>
			<ymax>102</ymax>
		</bndbox>
	</object>
	<object>
		<name>aspa</name>
		<pose>Unspecified</pose>
		<truncated>0</truncated>
		<difficult>0</difficult>
		<bndbox>
			<xmin>606</xmin>
			<ymin>242</ymin>
			<xmax>638</xmax>
			<ymax>345</ymax>
		</bndbox>
	</object>
	<object>
		<name>aspa</name>
		<pose>Unspecified</pose>
		<truncated>0</truncated>
		<difficult>0</difficult>
		<bndbox>
			<xmin>532</xmin>
			<ymin>288</ymin>
			<xmax>549</xmax>
			<ymax>356</ymax>
		</bndbox>
	</object>
</annotation>
