<annotation>
	<folder>train</folder>
	<filename>10566.png</filename>
	<path>/home/aspa2/Neural_Networks/kaimai_simplified/Images/train/10566.png</path>
	<source>
		<database>Unknown</database>
	</source>
	<size>
		<width>960</width>
		<height>600</height>
		<depth>3</depth>
	</size>
	<segmented>0</segmented>
	<object>
		<name>aspa</name>
		<pose>Unspecified</pose>
		<truncated>0</truncated>
		<difficult>0</difficult>
		<bndbox>
			<xmin>571</xmin>
			<ymin>120</ymin>
			<xmax>604</xmax>
			<ymax>295</ymax>
		</bndbox>
	</object>
	<object>
		<name>aspa</name>
		<pose>Unspecified</pose>
		<truncated>0</truncated>
		<difficult>0</difficult>
		<bndbox>
			<xmin>740</xmin>
			<ymin>435</ymin>
			<xmax>861</xmax>
			<ymax>599</ymax>
		</bndbox>
	</object>
</annotation>
