<annotation>
	<folder>500</folder>
	<filename>263.png</filename>
	<path>C:\Users\sdh17\Documents\NN\500\263.png</path>
	<source>
		<database>Unknown</database>
	</source>
	<size>
		<width>960</width>
		<height>600</height>
		<depth>3</depth>
	</size>
	<segmented>0</segmented>
	<object>
		<name>aspa</name>
		<pose>Unspecified</pose>
		<truncated>0</truncated>
		<difficult>0</difficult>
		<bndbox>
			<xmin>82</xmin>
			<ymin>312</ymin>
			<xmax>301</xmax>
			<ymax>375</ymax>
		</bndbox>
	</object>
</annotation>
